rcpyci/__init__.py
rcpyci/core.py
rcpyci/im_ops.py
rcpyci/infoval.py
rcpyci/interface.py
rcpyci/pipelines.py
rcpyci/utils.py
rcpyci/visualise.py
rcpyci-0.10.0.dist-info/METADATA
rcpyci-0.10.0.dist-info/WHEEL
rcpyci-0.10.0.dist-info/top_level.txt
rcpyci-0.10.0.dist-info/RECORD
