Metadata-Version: 2.4
Name: rcpyci
Version: 0.10.0
Summary: Toolkit for reverse correlation classificiation images
Author: hvalev
Maintainer: hvalev
License-Expression: MIT
Project-URL: homepage, https://github.com/hvalev/rcpyci
Project-URL: repository, https://github.com/hvalev/rcpyci
Project-URL: documentation, https://github.com/hvalev/rcpyci
Classifier: Development Status :: 4 - Beta
Classifier: Operating System :: OS Independent
Classifier: Programming Language :: Python :: 3 :: Only
Classifier: Programming Language :: Python :: 3.10
Classifier: Programming Language :: Python :: 3.11
Classifier: Programming Language :: Python :: 3.12
Classifier: Programming Language :: Python :: 3.13
Requires-Python: >=3.10
Requires-Dist: pandas<3.0.0,>=2.2.2
Requires-Dist: pillow<11.0.0,>=10.3.0
Requires-Dist: numpy<2.0.0,>=1.24.4
Requires-Dist: scipy<2.0.0,>=1.13.1
Requires-Dist: joblib<2.0.0,>=1.4.2
Requires-Dist: tqdm<5.0.0,>=4.67.1
Provides-Extra: visu
Requires-Dist: streamlit<2.0.0,>=1.42.0; extra == "visu"
Provides-Extra: test
Requires-Dist: ruff<1.0.0,>=0.4.6; extra == "test"
Requires-Dist: pytest<9.0.0,>=8.2.1; extra == "test"
